LICENSE
MANIFEST.in
README.md
setup.py
assetmingle/__init__.py
assetmingle.egg-info/PKG-INFO
assetmingle.egg-info/SOURCES.txt
assetmingle.egg-info/dependency_links.txt
assetmingle.egg-info/entry_points.txt
assetmingle.egg-info/requires.txt
assetmingle.egg-info/top_level.txt