Metadata-Version: 1.1
Name: assetmingle
Version: 0.1.2
Summary: Convert image and file references in HTML and CSS files to data URLs
Home-page: https://github.com/mike-douglas/assetmingle
Author: Mike Douglas
Author-email: michael.j.douglas@gmail.com
License: UNKNOWN
Keywords: html,css,base64,dataurl
Platform: UNKNOWN
Classifier: Environment :: Console
Classifier: Topic :: Multimedia :: Graphics
Classifier: Topic :: Multimedia :: Graphics :: Presentation
Classifier: Topic :: Internet :: WWW/HTTP :: Site Management
Classifier: Topic :: Text Processing :: Markup :: HTML
Classifier: Topic :: Text Processing :: Filters
Classifier: Topic :: Utilities
Classifier: Programming Language :: Python
